scrape_cli/__init__.py
scrape_cli/scrape.py
scrape_cli-1.2.0.dist-info/METADATA
scrape_cli-1.2.0.dist-info/WHEEL
scrape_cli-1.2.0.dist-info/entry_points.txt
scrape_cli-1.2.0.dist-info/top_level.txt
scrape_cli-1.2.0.dist-info/RECORD
