Metadata-Version: 2.4
Name: scrape_cli
Version: 1.2.0
Summary: It's a command-line tool to extract HTML elements using an XPath query or CSS3 selector.
Home-page: https://github.com/aborruso/scrape-cli
Author: Andrea Borruso
Author-email: Andrea Borruso <aborruso@gmail.com>
Project-URL: Homepage, https://github.com/aborruso/scrape-cli
Classifier: Programming Language :: Python :: 3
Classifier: Operating System :: OS Independent
Requires-Python: >=3.6
Requires-Dist: cssselect
Requires-Dist: lxml
Requires-Dist: requests
Dynamic: author
Dynamic: home-page
Dynamic: requires-python
